CHANGES.txt
MANIFEST.in
README.txt
TODO.txt
setup.py
django_inactive_user_workflow.egg-info/PKG-INFO
django_inactive_user_workflow.egg-info/SOURCES.txt
django_inactive_user_workflow.egg-info/dependency_links.txt
django_inactive_user_workflow.egg-info/entry_points.txt
django_inactive_user_workflow.egg-info/not-zip-safe
django_inactive_user_workflow.egg-info/requires.txt
django_inactive_user_workflow.egg-info/top_level.txt
inactive_user_workflow/__init__.py
inactive_user_workflow/forms.py
inactive_user_workflow/lib.py
inactive_user_workflow/middleware.py
inactive_user_workflow/urls.py
inactive_user_workflow/management/__init__.py
inactive_user_workflow/management/commands/__init__.py
inactive_user_workflow/management/commands/resend_activation_email.py
inactive_user_workflow/views/__init__.py
inactive_user_workflow/views/login.py
inactive_user_workflow/views/register.py
templates/registration/inactive_user.html