Metadata-Version: 1.0
Name: django-inactive-user-workflow
Version: 0.1
Summary: tools to let inactive users log in to your site with limited access after registration until they confirm their account
Home-page: UNKNOWN
Author: Ethan Jucovy
Author-email: ethan.jucovy@gmail.com
License: GPLv3 or greater
Keywords: django registration
Platform: UNKNOWN
Classifier: Framework :: Django
